{
  "text_id": "russian-fairy-tales",
  "tradition": "european",
  "source_file": "C:\\Users\\User\\Documents\\0000000\\mythic library\\texts\\european\\russian-fairy-tales\\normalized\\russian-fairy-tales_best.txt",
  "strategy": "structural",
  "segment_count": 47,
  "segments": [
    {
      "id": "seg_001",
      "label": "preamble",
      "segment_type": "preamble",
      "file": "seg_001_preamble.txt",
      "word_count": 681,
      "start_line": 0,
      "end_line": 100
    },
    {
      "id": "seg_002",
      "label": "chapter could grant; and therefore, though not without reluctance, I",
      "segment_type": "chapter",
      "file": "seg_002_chapter-could-grant-and-therefore-though.txt",
      "word_count": 954,
      "start_line": 101,
      "end_line": 224
    },
    {
      "id": "seg_003",
      "label": "CHAPTER I",
      "segment_type": "chapter",
      "file": "seg_003_chapter-i.txt",
      "word_count": 43,
      "start_line": 225,
      "end_line": 235
    },
    {
      "id": "seg_004",
      "label": "CHAPTER II",
      "segment_type": "chapter",
      "file": "seg_004_chapter-ii.txt",
      "word_count": 82,
      "start_line": 236,
      "end_line": 251
    },
    {
      "id": "seg_005",
      "label": "CHAPTER III",
      "segment_type": "chapter",
      "file": "seg_005_chapter-iii.txt",
      "word_count": 49,
      "start_line": 252,
      "end_line": 265
    },
    {
      "id": "seg_006",
      "label": "CHAPTER IV",
      "segment_type": "chapter",
      "file": "seg_006_chapter-iv.txt",
      "word_count": 53,
      "start_line": 266,
      "end_line": 276
    },
    {
      "id": "seg_007",
      "label": "CHAPTER V",
      "segment_type": "chapter",
      "file": "seg_007_chapter-v.txt",
      "word_count": 43,
      "start_line": 277,
      "end_line": 287
    },
    {
      "id": "seg_008",
      "label": "CHAPTER VI",
      "segment_type": "chapter",
      "file": "seg_008_chapter-vi.txt",
      "word_count": 362,
      "start_line": 288,
      "end_line": 420
    },
    {
      "id": "seg_009",
      "label": "CHAPTER I",
      "segment_type": "chapter",
      "file": "seg_009_chapter-i.txt",
      "word_count": 2448,
      "start_line": 421,
      "end_line": 648
    },
    {
      "id": "seg_010",
      "label": "chapter contains have been selected. Any information they may convey",
      "segment_type": "chapter",
      "file": "seg_010_chapter-contains-have-been-selected-any-.txt",
      "word_count": 3098,
      "start_line": 649,
      "end_line": 1090
    },
    {
      "id": "seg_011",
      "label": "The second story will serve as an illustration of one of the Russian",
      "segment_type": "tale",
      "file": "seg_011_the-second-story-will-serve-as-an-illust.txt",
      "word_count": 6694,
      "start_line": 1091,
      "end_line": 1865
    },
    {
      "id": "seg_012",
      "label": "story of the _Golovikha_. It is all the more valuable, inasmuch as it",
      "segment_type": "tale",
      "file": "seg_012_story-of-the-golovikha-it-is-all-the-mor.txt",
      "word_count": 7584,
      "start_line": 1866,
      "end_line": 2917
    },
    {
      "id": "seg_013",
      "label": "CHAPTER II",
      "segment_type": "chapter",
      "file": "seg_013_chapter-ii.txt",
      "word_count": 1279,
      "start_line": 2918,
      "end_line": 3044
    },
    {
      "id": "seg_014",
      "label": "story of",
      "segment_type": "tale",
      "file": "seg_014_story-of.txt",
      "word_count": 1748,
      "start_line": 3045,
      "end_line": 3238
    },
    {
      "id": "seg_015",
      "label": "the patriarch of the Russian story does not injure his captive. He",
      "segment_type": "tale",
      "file": "seg_015_the-patriarch-of-the-russian-story-does-.txt",
      "word_count": 2941,
      "start_line": 3239,
      "end_line": 3557
    },
    {
      "id": "seg_016",
      "label": "story of Sringabhuja, in chap. xxxix. of book vii. of",
      "segment_type": "tale",
      "file": "seg_016_story-of-sringabhuja-in-chap-xxxix-of-bo.txt",
      "word_count": 1067,
      "start_line": 3558,
      "end_line": 3662
    },
    {
      "id": "seg_017",
      "label": "story of \"Usuinya,\"[96] for instance, there appears to be no",
      "segment_type": "tale",
      "file": "seg_017_story-of-usuinya96-for-instance-there-ap.txt",
      "word_count": 4255,
      "start_line": 3663,
      "end_line": 4262
    },
    {
      "id": "seg_018",
      "label": "The story of Immortal Koshchei is one of very frequent occurrence,",
      "segment_type": "tale",
      "file": "seg_018_the-story-of-immortal-koshchei-is-one-of.txt",
      "word_count": 4721,
      "start_line": 4263,
      "end_line": 4802
    },
    {
      "id": "seg_019",
      "label": "the Indian story of \"Punchkin,\"[134] whose life depends on that of a",
      "segment_type": "tale",
      "file": "seg_019_the-indian-story-of-punchkin134-whose-li.txt",
      "word_count": 2224,
      "start_line": 4803,
      "end_line": 5061
    },
    {
      "id": "seg_020",
      "label": "story of this kind was doubtless founded the legend",
      "segment_type": "tale",
      "file": "seg_020_story-of-this-kind-was-doubtless-founded.txt",
      "word_count": 6198,
      "start_line": 5062,
      "end_line": 5829
    },
    {
      "id": "seg_021",
      "label": "part is played by the Baba Yaga, a female fiend whose name has given",
      "segment_type": "part",
      "file": "seg_021_part-is-played-by-the-baba-yaga-a-female.txt",
      "word_count": 2441,
      "start_line": 5830,
      "end_line": 6089
    },
    {
      "id": "seg_022",
      "label": "The rest of the story is very similar to that of \"Norka,\" which has",
      "segment_type": "tale",
      "file": "seg_022_the-rest-of-the-story-is-very-similar-to.txt",
      "word_count": 4492,
      "start_line": 6090,
      "end_line": 6605
    },
    {
      "id": "seg_023",
      "label": "story of \"Allerleirauh,\"[195] except in so far as the puppets are",
      "segment_type": "tale",
      "file": "seg_023_story-of-allerleirauh195-except-in-so-fa.txt",
      "word_count": 475,
      "start_line": 6606,
      "end_line": 6669
    },
    {
      "id": "seg_024",
      "label": "the solitary story in which he is mentioned. There were two old folks",
      "segment_type": "tale",
      "file": "seg_024_the-solitary-story-in-which-he-is-mentio.txt",
      "word_count": 4345,
      "start_line": 6670,
      "end_line": 7217
    },
    {
      "id": "seg_025",
      "label": "the Russian story the mouse jumps about on the strings",
      "segment_type": "tale",
      "file": "seg_025_the-russian-story-the-mouse-jumps-about-.txt",
      "word_count": 4308,
      "start_line": 7218,
      "end_line": 7844
    },
    {
      "id": "seg_026",
      "label": "CHAPTER III",
      "segment_type": "chapter",
      "file": "seg_026_chapter-iii.txt",
      "word_count": 1066,
      "start_line": 7845,
      "end_line": 7992
    },
    {
      "id": "seg_027",
      "label": "The opening of the story of Likho is somewhat similar to that of one",
      "segment_type": "tale",
      "file": "seg_027_the-opening-of-the-story-of-likho-is-som.txt",
      "word_count": 168,
      "start_line": 7993,
      "end_line": 8007
    },
    {
      "id": "seg_028",
      "label": "The Polyphemus story has been so thoroughly investigated by Wilhelm",
      "segment_type": "tale",
      "file": "seg_028_the-polyphemus-story-has-been-so-thoroug.txt",
      "word_count": 177,
      "start_line": 8008,
      "end_line": 8024
    },
    {
      "id": "seg_029",
      "label": "the Russian tales in a very archaic and heathenish form. Here is the",
      "segment_type": "tale",
      "file": "seg_029_the-russian-tales-in-a-very-archaic-and-.txt",
      "word_count": 4997,
      "start_line": 8025,
      "end_line": 8664
    },
    {
      "id": "seg_030",
      "label": "story of--",
      "segment_type": "tale",
      "file": "seg_030_story-of.txt",
      "word_count": 10407,
      "start_line": 8665,
      "end_line": 9949
    },
    {
      "id": "seg_031",
      "label": "CHAPTER IV",
      "segment_type": "chapter",
      "file": "seg_031_chapter-iv.txt",
      "word_count": 218,
      "start_line": 9950,
      "end_line": 9974
    },
    {
      "id": "seg_032",
      "label": "the Russian and the Western tales agree, but the Skazka differs from",
      "segment_type": "tale",
      "file": "seg_032_the-russian-and-the-western-tales-agree-.txt",
      "word_count": 7049,
      "start_line": 9975,
      "end_line": 10811
    },
    {
      "id": "seg_033",
      "label": "the Russian story disappears. For a solar explanation",
      "segment_type": "tale",
      "file": "seg_033_the-russian-story-disappears-for-a-solar.txt",
      "word_count": 5275,
      "start_line": 10812,
      "end_line": 11417
    },
    {
      "id": "seg_034",
      "label": "The horror of the next story is somewhat mitigated by a slight",
      "segment_type": "tale",
      "file": "seg_034_the-horror-of-the-next-story-is-somewhat.txt",
      "word_count": 6041,
      "start_line": 11418,
      "end_line": 12183
    },
    {
      "id": "seg_035",
      "label": "The obscurity of the Celtic tale forms a striking contrast to the",
      "segment_type": "tale",
      "file": "seg_035_the-obscurity-of-the-celtic-tale-forms-a.txt",
      "word_count": 1389,
      "start_line": 12184,
      "end_line": 12401
    },
    {
      "id": "seg_036",
      "label": "story of \"Pervonto\" (Basile's \"Pentamerone,\" No. 3) who obtains his",
      "segment_type": "tale",
      "file": "seg_036_story-of-pervonto-basiles-pentamerone-no.txt",
      "word_count": 485,
      "start_line": 12402,
      "end_line": 12478
    },
    {
      "id": "seg_037",
      "label": "CHAPTER V",
      "segment_type": "chapter",
      "file": "seg_037_chapter-v.txt",
      "word_count": 3782,
      "start_line": 12479,
      "end_line": 12926
    },
    {
      "id": "seg_038",
      "label": "The rest of the story closely resembles the German tale of \"The",
      "segment_type": "tale",
      "file": "seg_038_the-rest-of-the-story-closely-resembles-.txt",
      "word_count": 7368,
      "start_line": 12927,
      "end_line": 13889
    },
    {
      "id": "seg_039",
      "label": "CHAPTER VI",
      "segment_type": "chapter",
      "file": "seg_039_chapter-vi.txt",
      "word_count": 9395,
      "start_line": 13890,
      "end_line": 14955
    },
    {
      "id": "seg_040",
      "label": "II",
      "segment_type": "section",
      "file": "seg_040_ii.txt",
      "word_count": 5450,
      "start_line": 14956,
      "end_line": 15625
    },
    {
      "id": "seg_041",
      "label": "The rest of the story tells how the imp taught Isidore to make",
      "segment_type": "tale",
      "file": "seg_041_the-rest-of-the-story-tells-how-the-imp-.txt",
      "word_count": 2730,
      "start_line": 15626,
      "end_line": 16147
    },
    {
      "id": "seg_042",
      "label": "the story of Verlioka, 170;",
      "segment_type": "tale",
      "file": "seg_042_the-story-of-verlioka-170.txt",
      "word_count": 189,
      "start_line": 16148,
      "end_line": 16195
    },
    {
      "id": "seg_043",
      "label": "story of the Priest of, 355",
      "segment_type": "tale",
      "file": "seg_043_story-of-the-priest-of-355.txt",
      "word_count": 196,
      "start_line": 16196,
      "end_line": 16262
    },
    {
      "id": "seg_044",
      "label": "story of Elijah and Nicholas, 344;",
      "segment_type": "tale",
      "file": "seg_044_story-of-elijah-and-nicholas-344.txt",
      "word_count": 68,
      "start_line": 16263,
      "end_line": 16283
    },
    {
      "id": "seg_045",
      "label": "story of Ivan Popyalof, 79;",
      "segment_type": "tale",
      "file": "seg_045_story-of-ivan-popyalof-79.txt",
      "word_count": 5,
      "start_line": 16284,
      "end_line": 16284
    },
    {
      "id": "seg_046",
      "label": "story of the Water Snake, 126;",
      "segment_type": "tale",
      "file": "seg_046_story-of-the-water-snake-126.txt",
      "word_count": 790,
      "start_line": 16285,
      "end_line": 16482
    },
    {
      "id": "seg_047",
      "label": "the story of Helena the Fair ...\"",
      "segment_type": "tale",
      "file": "seg_047_the-story-of-helena-the-fair.txt",
      "word_count": 1131,
      "start_line": 16483,
      "end_line": 16736
    }
  ]
}