{
  "source_format": "sacred-texts",
  "text_id": "pyramid-texts",
  "source_url": "https://sacred-texts.com/egy/pyt/index.htm",
  "download_date": "2026-01-25T05:53:03.030553",
  "title": "The Pyramid Texts",
  "author": "Anonymous",
  "tradition": "egyptian",
  "date_composed": "c. 2400-2300 BCE",
  "material_type": "Funerary texts",
  "original_file": "sacred-texts_egy_pyt_index.htm_Samuel-A.B.-Mercer.txt",
  "normalization_date": "2026-01-26T10:04:02.811070",
  "char_count": 6154,
  "line_count": 133,
  "word_count": 943
}